README.md
setup.cfg
setup.py
ciscosparkbot/Spark.py
ciscosparkbot/__about__.py
ciscosparkbot/__init__.py
ciscosparkbot/models.py
ciscosparkbot.egg-info/PKG-INFO
ciscosparkbot.egg-info/SOURCES.txt
ciscosparkbot.egg-info/dependency_links.txt
ciscosparkbot.egg-info/requires.txt
ciscosparkbot.egg-info/top_level.txt