Metadata-Version: 1.0
Name: ciscosparkbot
Version: 0.6.2
Summary: Python Bot for Cisco Spark
Home-page: http://github.com/imapex/ciscosparkbot
Author: Cisco Systems, Inc.
Author-email: imapex-admin@cisco.com
License: Apache License, Version 2.0
Platform: UNKNOWN
